odoo/addons/sale_start_end_dates/README.rst
odoo/addons/sale_start_end_dates/__init__.py
odoo/addons/sale_start_end_dates/__manifest__.py
odoo/addons/sale_start_end_dates/i18n/ca.po
odoo/addons/sale_start_end_dates/i18n/de.po
odoo/addons/sale_start_end_dates/i18n/el_GR.po
odoo/addons/sale_start_end_dates/i18n/es.po
odoo/addons/sale_start_end_dates/i18n/es_ES.po
odoo/addons/sale_start_end_dates/i18n/es_VE.po
odoo/addons/sale_start_end_dates/i18n/fi.po
odoo/addons/sale_start_end_dates/i18n/fr.po
odoo/addons/sale_start_end_dates/i18n/hr.po
odoo/addons/sale_start_end_dates/i18n/hr_HR.po
odoo/addons/sale_start_end_dates/i18n/hu.po
odoo/addons/sale_start_end_dates/i18n/it.po
odoo/addons/sale_start_end_dates/i18n/nl.po
odoo/addons/sale_start_end_dates/i18n/nl_NL.po
odoo/addons/sale_start_end_dates/i18n/pt.po
odoo/addons/sale_start_end_dates/i18n/pt_BR.po
odoo/addons/sale_start_end_dates/i18n/ro.po
odoo/addons/sale_start_end_dates/i18n/sale_start_end_dates.pot
odoo/addons/sale_start_end_dates/i18n/sk.po
odoo/addons/sale_start_end_dates/i18n/sl.po
odoo/addons/sale_start_end_dates/i18n/tr.po
odoo/addons/sale_start_end_dates/i18n/tr_TR.po
odoo/addons/sale_start_end_dates/i18n/vi_VN.po
odoo/addons/sale_start_end_dates/i18n/zh_CN.po
odoo/addons/sale_start_end_dates/models/__init__.py
odoo/addons/sale_start_end_dates/models/sale_order.py
odoo/addons/sale_start_end_dates/readme/CONTRIBUTORS.rst
odoo/addons/sale_start_end_dates/readme/DESCRIPTION.rst
odoo/addons/sale_start_end_dates/static/description/icon.png
odoo/addons/sale_start_end_dates/static/description/index.html
odoo/addons/sale_start_end_dates/tests/__init__.py
odoo/addons/sale_start_end_dates/tests/test_sale_start_end_dates.py
odoo/addons/sale_start_end_dates/views/sale_order.xml
odoo14_addon_sale_start_end_dates-14.0.1.0.1.dist-info/METADATA
odoo14_addon_sale_start_end_dates-14.0.1.0.1.dist-info/WHEEL
odoo14_addon_sale_start_end_dates-14.0.1.0.1.dist-info/top_level.txt
odoo14_addon_sale_start_end_dates-14.0.1.0.1.dist-info/RECORD
